autocar_automate_po/__init__.py
autocar_automate_po/automate_po_process.py
autocar_automate_po/print_po.py
autocar_automate_po-0.3.11.dist-info/LICENSE
autocar_automate_po-0.3.11.dist-info/WHEEL
autocar_automate_po-0.3.11.dist-info/METADATA
autocar_automate_po-0.3.11.dist-info/RECORD
