Metadata-Version: 2.1
Name: autocar_automate_po
Version: 0.3.11
Summary: autocar_po_automate
Home-page: https://github.com/MuseHorizon/autocar_automate_po
Author: Jean Henstock
Author-email: jjhenstockwork@gmail.com
Classifier: License :: OSI Approved :: MIT License
Requires-Dist: openpyxl
Requires-Dist: pandas
Requires-Dist: pyperclip
Requires-Dist: xlwings
